hw/branch_control.vhd
library IEEE;
use ieee.std_logic_1164.all;
use ieee.numeric_std.all;

library work;
use work.instructions.all;

entity Branch_control is -- a Control unit :)
  generic(
    bitwidth : integer := (32 - 1));
  port(
    clk 	: in std_ulogic;
    rst		: in std_ulogic;
    branch 	:out std_ulogic; -- when this is set it will change the PC to in 
    misaligned  :out std_ulogic; -- error bit

    inst_enum_in: in instruction_all;
    inst_in	: in std_ulogic_vector(bitwidth downto 0); 
    rs1_in	: in std_ulogic_vector(bitwidth downto 0);
    rs2_in	: in std_ulogic_vector(bitwidth downto 0);

    acc_out     :out std_ulogic_vector(bitwidth downto 0); 
    
    PC_in	: in std_ulogic_vector(bitwidth downto 0); 			
    PC_out	:out std_ulogic_vector(bitwidth downto 0);
    acc_me 	:out std_ulogic
    );
end Branch_control;


architecture Control_arch of Branch_control is
  
begin
  process(clk)
    variable imm	 	: std_ulogic_vector(bitwidth + 1 downto 0);
    variable temp		: signed(bitwidth + 1 downto 0);
    variable branched 	: std_ulogic := '0'; --unconditional jumps
    variable branch_c	: std_ulogic := '0'; --conditional jumps
    --When branched or branch_c is set high 
  begin
    
    if rst = '0' then --reset on low
      acc_me <= '0';
      misaligned <= '0';
      branched := '0';
      branch_c := '0';
      imm := (others => '0');
      PC_out <= (others => '0'); --default 0, only used in
      acc_out <= (others => '0'); --default 0, only used in JALR
      branch <= '0';
      
    elsif rising_edge(clk) then

      misaligned <= '0';
      branched := '0';
      branch_c := '0';

      imm := (others => '0');

      PC_out <= (others => '0'); --deafault to 0s

      acc_out <= (others => '0'); --deafault low, only used in JALR
      acc_me <= '0';

------------------------conditional jumps------------------------
      case inst_enum_in is
        when iBEQ =>
          if rs1_in = rs2_in then
            branch_c := '1';
          end if;
        when iBNE =>
          if rs1_in /= rs2_in then
            branch_c := '1';
          end if;	
        when iBLT =>
          if signed(rs1_in) < signed(rs2_in) then
            branch_c := '1';
          end if;
        when iBGE =>
          if signed(rs1_in) >= signed(rs2_in) then
            branch_c := '1';
          end if;
        when iBGEU =>
          if unsigned(rs1_in) >= unsigned(rs2_in) then
            branch_c := '1';
          end if;
        when iBLTU =>
          if unsigned(rs1_in) < unsigned(rs2_in) then
            branch_c := '1';
          end if;
-----------------------unconditional jumps-----------------------
        when iJAL =>
          branched := '1';
          imm(20 downto 0) := (inst_in(31) & inst_in(19 downto 12) & inst_in(20) & inst_in(30 downto 21) &'0');--set imm for	--(others => '0') or
          imm(bitwidth downto 21) := (others => inst_in(31));
          
        when iJALR => -- this does not calculate PC the same and is not complete without code after
          branched := '1';
          acc_out <= std_ulogic_vector(unsigned(PC_in) + 4);
          acc_me <= '1';
          imm(11 downto 0) := inst_in(bitwidth downto 20);			
          imm(bitwidth downto 12) := (others => inst_in(bitwidth));
------------------------ LUI AND AUIPC ------------------------
        when iLUI =>
          acc_out(31 downto 12) <= inst_in(31 downto 12);
          acc_out(11 downto 0 ) <= (others => '0');
          acc_me <= '1';
        when iAUIPC =>
          imm(31 downto 12) :=  inst_in(31 downto 12);
          imm(11 downto 0 ) := (others => '0');
          temp := signed('0' & PC_in) + signed(imm);
          acc_out(31 downto 0) <= std_ulogic_vector(temp(31 downto 0));
          
        when others =>
          branched := '0';
      end case;

----------------------- manage branches ------------------------
      if (branch_c or branched) = '1' then 
        if branch_c = '1' then -- set branched and imm for conditional branches
          branched := '1';
          imm(12 downto 0) := (inst_in(31) & inst_in(7) & inst_in(30 downto 25) & inst_in(11 downto 8) & '0');
          imm(bitwidth downto 13) := (others => inst_in(31));
        end if;

-------------------------JALR exception-------------------------
        if inst_enum_in = iJALR then
          temp := signed('0' & rs1_in)+ signed(imm);
--------------------add imm and set PC_out----------------------	
        else
          temp := signed('0' & PC_in) + signed(imm);
        end if;
        PC_out(bitwidth downto 0) <= std_ulogic_vector(temp(bitwidth downto 0));
        
        misaligned <= (temp(0) or temp(1)); --find if bytes aligne with 32 bit register space
        
      end if;
      branch <= branched;
    end if;
    
  end process;

end Control_arch;

tb/branch_control_tb.vhd
library ieee;
use ieee.std_logic_1164.all;
use ieee.numeric_std.all;

library work; 
use work.tb_helpers.all;
use work.assembler.all;

-- This whole testbench is a bit of a mess, written before I used the newer
-- test functions & VHDL assembler, but it still works :) although hard to read 
-- indentation is OK but a little messed up with the comments, this was first
-- written in gedit

entity tb_Branch_control is
  generic(bitwidth : integer := (32-1) 		--size of access bus
          );
end tb_Branch_control;

architecture tb of tb_Branch_control is

  component Branch_control
    port (clk        : in std_ulogic;
          rst        : in std_ulogic;
          branch     : out std_ulogic;
          misaligned : out std_ulogic;
          inst_in    : in std_ulogic_vector (bitwidth downto 0);
          rs1_in     : in std_ulogic_vector (bitwidth downto 0);
          rs2_in     : in std_ulogic_vector (bitwidth downto 0);
          acc_out    : out std_ulogic_vector (bitwidth downto 0);
          PC_in      : in std_ulogic_vector (bitwidth downto 0);
          PC_out     : out std_ulogic_vector (bitwidth downto 0);
          acc_me     : out std_ulogic);
  end component;

  signal clk        : std_ulogic;
  signal rst        : std_ulogic;
  signal branch     : std_ulogic;
  signal misaligned : std_ulogic;
  signal inst_in    : std_ulogic_vector (bitwidth downto 0);
  signal rs1_in     : std_ulogic_vector (bitwidth downto 0);
  signal rs2_in     : std_ulogic_vector (bitwidth downto 0);
  signal acc_out    : std_ulogic_vector (bitwidth downto 0);
  signal PC_in      : std_ulogic_vector (bitwidth downto 0);
  signal PC_out     : std_ulogic_vector (bitwidth downto 0);
  signal acc_me     : std_ulogic;

  constant TbPeriod : time := 1000 ns; -- EDIT Put right period here
  signal TbClock : std_logic := '0';
  signal TbSimEnded : std_logic := '0';

begin

  dut : Branch_control
    port map (clk        => clk,
              rst        => rst,
              branch     => branch,
              misaligned => misaligned,
              inst_in    => inst_in,
              rs1_in     => rs1_in,
              rs2_in     => rs2_in,
              acc_out    => acc_out,
              PC_in      => PC_in,
              PC_out     => PC_out,
              acc_me     => acc_me);

  -- Clock generation
  TbClock <= not TbClock after TbPeriod/2 when TbSimEnded /= '1' else '0';

  -- EDIT: Check that clk is really your main clock signal
  clk <= TbClock;

  stimuli : process
    variable clk_count 	: integer := 0;     
    variable clk_max 	: integer := 16;
    variable zeros		: std_ulogic_vector(bitwidth downto 0) := (others => '0'); --used for padding
  begin
    -- EDIT Adapt initialization as needed
    inst_in <= (others => '0');
    rs1_in <= (others => '0');
    rs2_in <= (others => '0');
    PC_in <= (others => '0');

    -- Reset generation
    -- EDIT: Check that rst is really your reset signal
    rst <= '0';
    wait for 100 ns;
    rst <= '1';
    wait for 100 ns;
    
    for clk_count in 0 to clk_max loop
      case clk_count is 
        when 0 =>
					-- JAL test
          inst_in <= "00000001011000000000001001101111"; --rs1: 2 , rs2: 3, rd 4 , 22 imm
                                                         --no command test
          test_1( branch, '0', "Branch flag off");
        when 1 =>
					--JAL negtaive test
          inst_in <= "11111111111111111111000001101111"; -- rs1: 0 , rs2: 0, rd 0 , (- 2) imm
          pc_in <= int2ulogic32(20);
          
					--JAL test
          test_32(pc_out, int2ulogic32(22), "JAL unsigned");
          test_1(branch, '1', "Branch flag on");		
        when 2 =>
					--JALR
          inst_in <= "00000001011100011000001011100111";-- rs1: 3 , rs2: 4, rd 5 , 23 imm
          rs1_in <= int2ulogic32(4);
					-- JAL signed test
          test_32(pc_out, int2ulogic32(18), "JAL signed");
        when 3 =>
					--BEQ fail
          inst_in <= "00000001100000000000001101100011";-- rs1: 4 , rs2: 5, rd 6 , 24 imm
          rs1_in <= int2ulogic32(5);
          rs2_in <= int2ulogic32(525);
					--JALR test
          test_32(pc_out ,int2ulogic32(27), "JALR RS1");
          test_1(acc_me, '1', "JALR write flag");
          test_32(acc_out, int2ulogic32(24), "JALR write val");
        when 4 =>
					--BEQ PASS
          rs1_in <= int2ulogic32(14);
          rs2_in <= int2ulogic32(14);
					--BEQ fail
          test_1(branch, '0', "BEQ fail");
					-- add a test on PC_out
        when 5 =>
					--BNE
          inst_in <="00000000000000000001000001100011";-- rs1: 5 , rs2: 6, rd 7 , 25 imm
                                                       --BEQ pass
          test_1(branch, '1', "BEQ branch");
					-- add a test on PC_out

        when 6 =>
					--BNE pass test 
          rs1_in <= int2ulogic32(1004);
          
					--BNE fail test
          test_1(branch, '0', "BNE nothing");
          

        when 7 =>
					--BLT fail
          inst_in <="00000000000000000100000001100011";-- rs1: 6 , rs2: 7, rd 8 , 26 imm
          rs2_in <= sint2ulog32(-44);
          
					-- BNE pass
          test_1(branch, '1', "BNE branch");
        when 8 =>
					--BLT pass
          rs1_in<= sint2ulog32(-50);
					--BLT fail
          test_1(branch, '0', "BLT fail");
          
        when 9 =>
					--BGE fail
          inst_in <="00000000000000000101000001100011";-- rs1: 7 , rs2: 8, rd 9 , 27 imm
          
					-- BLT pass
          test_1(branch, '1', "BLT branch");
        when 10 =>
					--BGE pass
          rs1_in<= sint2ulog32(55);
					--BGE fail
          test_1(branch, '0', "BGE nothing");	
          
        when 11 =>
					--BLTU fail
          inst_in <="00000000000000000110000001100011";
          rs1_in<= int2ulogic32(50);
          rs2_in <= int2ulogic32(50);
          
					-- BGE pass
          test_1(branch, '1', "BGE branch");
        when 12 =>
					--BLTU pass
          rs1_in<= int2ulogic32(2);
          rs2_in <= int2ulogic32(40000);
					--BLTU fail
          test_1(branch, '0', "BLTU nothing");
        when 13 =>
					--BGEU fail
          inst_in <="00000000000000000111000001100011";		
					--BLTU pass
          test_1(branch, '1', "BLTU branch");					
        when 14 =>
					--BGEU pass
          rs1_in<= sint2ulog32(1000);
          rs2_in <= sint2ulog32(10);
					--BGEU fail
          test_1(branch, '0', "BGEU nothing");
        when 15 =>
          test_1(branch, '1', "BGEU branch");
          
          rs1_in <= sint2ulog32(200);
          RISCV32I(iJALR, 0, 0, 0,-35);
        when 16 =>
          test_against_uint(PC_out, 165, "JALR return minus");
        when others =>
          null;
      end case;
      wait for TbPeriod;
    end loop;
    
    -- Stop the clock and hence terminate the simulation
    TbSimEnded <= '1';
    wait;
  end process;

end tb;

-- Configuration block below is required by some simulators. Usually no need to edit.

configuration cfg_tb_Branch_control of tb_Branch_control is
  for tb
  end for;
end cfg_tb_Branch_control;

sim/tb_branch_control.vcd
$date
  Thu Feb  4 15:15:00 2021
$end
$version
  GHDL v0
$end
$timescale
  1 fs
$end
$scope module standard $end
$upscope $end
$scope module std_logic_1164 $end
$upscope $end
$scope module numeric_std $end
$upscope $end
$scope module riscv_32i $end
$upscope $end
$scope module helpers $end
$upscope $end
$scope module tb_helpers $end
$upscope $end
$scope module tb_branch_control $end
$var reg 1 ! clk $end
$var reg 1 " rst $end
$var reg 1 # branch $end
$var reg 1 $ misaligned $end
$var reg 32 % inst_in[31:0] $end
$var reg 32 & rs1_in[31:0] $end
$var reg 32 ' rs2_in[31:0] $end
$var reg 32 ( acc_out[31:0] $end
$var reg 32 ) pc_in[31:0] $end
$var reg 32 * pc_out[31:0] $end
$var reg 1 + acc_me $end
$var reg 1 , tbclock $end
$var reg 1 - tbsimended $end
$scope module dut $end
$var reg 1 . clk $end
$var reg 1 / rst $end
$var reg 1 0 branch $end
$var reg 1 1 misaligned $end
$var reg 32 2 inst_in[31:0] $end
$var reg 32 3 rs1_in[31:0] $end
$var reg 32 4 rs2_in[31:0] $end
$var reg 32 5 acc_out[31:0] $end
$var reg 32 6 pc_in[31:0] $end
$var reg 32 7 pc_out[31:0] $end
$var reg 1 8 acc_me $end
$upscope $end
$upscope $end
$enddefinitions $end
#0
0!
0"
0#
0$
b00000000000000000000000000000000 %
b00000000000000000000000000000000 &
b00000000000000000000000000000000 '
b00000000000000000000000000000000 (
b00000000000000000000000000000000 )
b00000000000000000000000000000000 *
0+
0,
0-
0.
0/
00
01
b00000000000000000000000000000000 2
b00000000000000000000000000000000 3
b00000000000000000000000000000000 4
b00000000000000000000000000000000 5
b00000000000000000000000000000000 6
b00000000000000000000000000000000 7
08
#100000000
1"
1/
#200000000
b00000001011000000000001001101111 %
b00000001011000000000001001101111 2
#500000000
1!
1#
1$
b00000000000000000000000000010110 *
1,
1.
10
11
b00000000000000000000000000010110 7
#1000000000
0!
0,
0.
#1200000000
b11111111111111111111000001101111 %
b00000000000000000000000000010100 )
b11111111111111111111000001101111 2
b00000000000000000000000000010100 6
#1500000000
1!
b00000000000000000000000000010010 *
1,
1.
11
b00000000000000000000000000010010 7
#2000000000
0!
0,
0.
#2200000000
b00000001011100011000001011100111 %
b00000000000000000000000000000100 &
b00000001011100011000001011100111 2
b00000000000000000000000000000100 3
#2500000000
1!
b00000000000000000000000000011000 (
b00000000000000000000000000011011 *
1+
1,
1.
11
b00000000000000000000000000011000 5
b00000000000000000000000000011011 7
18
#3000000000
0!
0,
0.
#3200000000
b00000001100000000000001101100011 %
b00000000000000000000000000000101 &
b00000000000000000000001000001101 '
b00000001100000000000001101100011 2
b00000000000000000000000000000101 3
b00000000000000000000001000001101 4
#3500000000
1!
0#
0$
b00000000000000000000000000000000 (
b00000000000000000000000000000000 *
0+
1,
1.
00
01
b00000000000000000000000000000000 5
b00000000000000000000000000000000 7
08
#4000000000
0!
0,
0.
#4200000000
b00000000000000000000000000001110 &
b00000000000000000000000000001110 '
b00000000000000000000000000001110 3
b00000000000000000000000000001110 4
#4500000000
1!
1#
1$
b00000000000000000000000000011010 *
1,
1.
10
11
b00000000000000000000000000011010 7
#5000000000
0!
0,
0.
#5200000000
b00000000000000000001000001100011 %
b00000000000000000001000001100011 2
#5500000000
1!
0#
0$
b00000000000000000000000000000000 *
1,
1.
00
01
b00000000000000000000000000000000 7
#6000000000
0!
0,
0.
#6200000000
b00000000000000000000001111101100 &
b00000000000000000000001111101100 3
#6500000000
1!
1#
b00000000000000000000000000010100 *
1,
1.
10
b00000000000000000000000000010100 7
#7000000000
0!
0,
0.
#7200000000
b00000000000000000100000001100011 %
b11111111111111111111111111010100 '
b00000000000000000100000001100011 2
b11111111111111111111111111010100 4
#7500000000
1!
0#
b00000000000000000000000000000000 *
1,
1.
00
b00000000000000000000000000000000 7
#8000000000
0!
0,
0.
#8200000000
b11111111111111111111111111001110 &
b11111111111111111111111111001110 3
#8500000000
1!
1#
b00000000000000000000000000010100 *
1,
1.
10
b00000000000000000000000000010100 7
#9000000000
0!
0,
0.
#9200000000
b00000000000000000101000001100011 %
b00000000000000000101000001100011 2
#9500000000
1!
0#
b00000000000000000000000000000000 *
1,
1.
00
b00000000000000000000000000000000 7
#10000000000
0!
0,
0.
#10200000000
b00000000000000000000000000110111 &
b00000000000000000000000000110111 3
#10500000000
1!
1#
b00000000000000000000000000010100 *
1,
1.
10
b00000000000000000000000000010100 7
#11000000000
0!
0,
0.
#11200000000
b00000000000000000110000001100011 %
b00000000000000000000000000110010 &
b00000000000000000000000000110010 '
b00000000000000000110000001100011 2
b00000000000000000000000000110010 3
b00000000000000000000000000110010 4
#11500000000
1!
0#
b00000000000000000000000000000000 *
1,
1.
00
b00000000000000000000000000000000 7
#12000000000
0!
0,
0.
#12200000000
b00000000000000000000000000000010 &
b00000000000000001001110001000000 '
b00000000000000000000000000000010 3
b00000000000000001001110001000000 4
#12500000000
1!
1#
b00000000000000000000000000010100 *
1,
1.
10
b00000000000000000000000000010100 7
#13000000000
0!
0,
0.
#13200000000
b00000000000000000111000001100011 %
b00000000000000000111000001100011 2
#13500000000
1!
0#
b00000000000000000000000000000000 *
1,
1.
00
b00000000000000000000000000000000 7
#14000000000
0!
0,
0.
#14200000000
b00000000000000000000001111101000 &
b00000000000000000000000000001010 '
b00000000000000000000001111101000 3
b00000000000000000000000000001010 4
#14500000000
1!
1#
b00000000000000000000000000010100 *
1,
1.
10
b00000000000000000000000000010100 7
#15000000000
0!
0,
0.
#15200000000
#15500000000
1!
1,
1.
b00000000000000000000000000010100 7
#16000000000
0!
0,
0.
#16200000000
1-
