hw/integer_32_alu.vhd
library IEEE;
use ieee.std_logic_1164.all;
use ieee.numeric_std.all;

library work;
use work.instructions.all;
use work.helpers.all;

entity Integer_32_ALU is
  generic( bitwidth : integer :=(32 -1));
  port(clk, rst 	: in std_ulogic;
       	        
       inst_in	        : in instruction; 
       inst_enum_in     : in instruction_all; 

       rs1_in, rs2_in	: in std_ulogic_vector(bitwidth downto 0);
       acc_out          :out std_ulogic_vector(bitwidth downto 0);
       acc_me           :out std_ulogic
   );
end Integer_32_ALU;

architecture ALU_arch of Integer_32_ALU is
  alias imm     : std_ulogic_vector(11 downto 0) is inst_in(bitwidth downto 20);
  alias shamt   : std_ulogic_vector(4 downto 0) is inst_in(24 downto 20);
  
begin
  process(clk)
  begin
    if rst = '0' then
      acc_out <= (others => '0');
      acc_me  <= '0';

    elsif rising_edge(clk) then       
      
      acc_me <= '1';
      
      case inst_enum_in  is
        when iADDI =>
          acc_out <= std_ulogic_vector(signed(rs1_in) + signed_extend(imm, rs1_in'length));
        when iSlTI =>
          --should set rd to 0, but this is handled by acc_me and the accumulator
          if not signed(rs1_in) < signed_extend(imm,rs1_in'length ) then
            acc_me <= '0';
          end if;
          acc_out <= X"00000001";
        when iSlTIU=>
          if not unsigned(rs1_in) < unsigned(X"00000" & imm) then  
            acc_me <= '0';
          end if;
          acc_out <= X"00000001";
        when iXORI =>
          acc_out <= rs1_in xor std_ulogic_vector(signed_extend(imm, bitwidth + 1));
        when iORI  =>
          acc_out <= rs1_in or std_ulogic_vector(signed_extend(imm, bitwidth + 1));  
        when iANDI =>
          acc_out <= rs1_in and std_ulogic_vector(signed_extend(imm,bitwidth + 1));
        when iSLLI =>
          acc_out <= lleft_shift(rs1_in,to_integer(unsigned(shamt)));
        when iSRLI =>
          acc_out <= lright_shift(rs1_in,to_integer(unsigned(shamt)));
        when iSRAI =>
          acc_out <= aright_shift(rs1_in,to_integer(unsigned(shamt)));
-- instructions do not make use of imm
        when iADD =>         
          acc_out <= std_ulogic_vector(signed(rs1_in) + signed(rs2_in));
        when iSUB =>
          acc_out <= std_ulogic_vector(signed(rs1_in) - signed(rs2_in));
        when iSLL =>
          acc_out <= lleft_shift(rs1_in,to_integer(unsigned(rs2_in(4 downto 0))));
        when iSLT =>
          if not  signed(rs1_in) < signed(rs2_in) then
            acc_me <= '0';
          end if;
          acc_out <= X"00000001";
        when iSLTU=>
          if not unsigned(rs1_in) < unsigned(rs2_in) then
            acc_me <= '0';
          end if;     
          acc_out <= X"00000001";
        when iXOR =>
          acc_out <= rs1_in xor rs2_in;
        when iSRL =>
          acc_out <= lright_shift(rs1_in,to_integer(unsigned(rs2_in(4 downto 0))));
        when iSRA =>
          acc_out <= aright_shift(rs1_in,to_integer(unsigned(rs2_in(4 downto 0))));
        when iOR  =>
          acc_out <= rs1_in or rs2_in;
        when iAND =>
          acc_out <= rs1_in and rs2_in;
        
        when others =>
          acc_me <= '0';
      end case;
    end if;
  end process;  
end ALU_arch;

tb/integer_32_ALU_tb.vhd
library ieee;
use ieee.std_logic_1164.all;
use ieee.numeric_std.all;

library work;
--use work.tb_helpers.all;
use work.all;

use work.instructions.all;
use work.assembler.all;
use work.tb_helpers.all;

entity tb_Integer_32_ALU is
  generic( bitwidth : integer :=(32 -1));
end tb_Integer_32_ALU;

architecture tb of tb_Integer_32_ALU is
  component Integer_32_ALU
    port (clk     : in std_ulogic;
          rst     : in std_ulogic;
          inst_in : in std_ulogic_vector (bitwidth downto 0);
          rs1_in  : in std_ulogic_vector (bitwidth downto 0);
          rs2_in  : in std_ulogic_vector (bitwidth downto 0);
          acc_out : out std_ulogic_vector (bitwidth downto 0);
          acc_me  : out std_ulogic);
  end component;

  signal clk     : std_ulogic;
  signal rst     : std_ulogic;
  signal inst_in : std_ulogic_vector (bitwidth downto 0);
  signal rs1_in  : std_ulogic_vector (bitwidth downto 0);
  signal rs2_in  : std_ulogic_vector (bitwidth downto 0);
  signal acc_out : std_ulogic_vector (bitwidth downto 0);
  signal acc_me  : std_ulogic;

  constant TbPeriod : time := 1000 ns; 
  signal TbClock : std_logic := '0';
  signal TbSimEnded : std_logic := '0';

begin

  dut : Integer_32_ALU
    port map (clk     => clk,
              rst     => rst,
              inst_in => inst_in,
              rs1_in  => rs1_in,
              rs2_in  => rs2_in,
              acc_out => acc_out,
              acc_me  => acc_me);

  -- Clock generation
  TbClock <= not TbClock after TbPeriod/2 when TbSimEnded /= '1' else '0';

  clk <= TbClock;
  stimuli : process
--declare variables
    variable clk_count 	: integer := 0;     
    variable clk_max 	: integer := 35;

  begin
    -- initialization 
    inst_in <= (others => '0');
    rs1_in <= (others => '0');
    rs2_in <= (others => '0');

    -- Reset generation
    rst <= '0';
    wait for 100 ns;
    rst <= '1';
    wait for 100 ns;

    for clk_count in 0 to clk_max loop
      case clk_count is
        when 0=>
          inst_in <= assembler.RISCV32I(iADDI, 0, 0, 0, 100);
          report "Test ulogic_vector_image function :" & ulogic_vector_image(assembler.RISCV32I(iADDI, 0, 0, 0, 100)) & " Passed :)";
        when 1 =>
          test_against_sint(acc_out, 100, "Add positive immedate");
          rs1_in <= sint2ulog32(1);
          inst_in <= assembler.RISCV32I(iADDI, 0, 0, 0, -325);
        when 2 =>
          test_against_sint(acc_out, -324, "Add negative immedate");
          inst_in <= assembler.RISCV32I(iSLTI, 0, 0, 0, 1);
        when 3=>
          test_1(acc_me, '0', "SLTI block select");
          
          inst_in <= assembler.RISCV32I(iSLTI, 0, 0, 0, -34);
          rs1_in <= sint2ulog32(-4000);
        when 4 =>
          test_against_uint(acc_out, 1, "SLTI pass data");
          test_1(acc_me, '1', "SLTI pass select");

          inst_in <= assembler.RISCV32I(iSLTIU, 0, 0, 0, 34);

        when 5 =>
          test_1(acc_me, '1', "SLTIU block select");

          inst_in <= assembler.RISCV32I(iSLTIU, 0, 0, 0, 255);
          rs1_in <= sint2ulog32(2);

        when 6 =>
          test_against_uint(acc_out, 1, "SLTIU pass data");
          test_1(acc_me, '1', "SLTIU pass select");

          inst_in <= assembler.RISCV32I(iXORI, 0, 0, 0, -1);
          rs1_in <= sint2ulog32(200);
        when 7 =>
          test_against_sint(acc_out, -201, "iXORI 1");
          
          inst_in <= assembler.RISCV32I(iXORI, 0, 0, 0, 0);
          rs1_in <= (others => '0');
        when 8 =>
          test_against_uint(acc_out, 0, "XORI 2");
          test_1(acc_me, '1', "XORI select");

          inst_in <= assembler.RISCV32I(iORI,0,0,0,0);
          rs1_in <= sint2ulog32(42534);
        when 9 =>
          test_against_sint(acc_out, 42534, "ORI 1");
          
          inst_in <= assembler.RISCV32I(iORI,0,0,0,-1); --should make
                                                           --the imm all 1s
          rs1_in <= X"FFFFFFFF";
        when 10 =>
          test_against_sint(acc_out, -1 , "ORI 2"); -- should be all 1s
          
          inst_in <= assembler.RISCV32I(iANDI,0,0,0,0);
          rs1_in <= sint2ulog32(42534);
        when 11 =>
          test_against_sint(acc_out, 0, "ANDI 0");
          
          inst_in <= assembler.RISCV32I(iANDI,0,0,0,-1); --should make
                                                            --the imm all 1s
          rs1_in <= sint2ulog32(15000);

        when 12 =>
          test_against_sint(acc_out, 15000, "ANDI 1");
          
          inst_in <= assembler.RISCV32I(iSLLI,0,0,0,1);
          rs1_in <= sint2ulog32(2);
        when 13 =>
          test_against_sint(acc_out, 4, "SSLI");
          
          inst_in <= assembler.RISCV32I(iSRLI, 0,0,0,1);
        when 14 =>
          test_against_sint(acc_out, 1, "SRLI");
          inst_in <= assembler.RISCV32I(iSRAI, 0,0,0,1);
          rs1_in <= sint2ulog32(-2);
        when 15 =>
          test_against_sint(acc_out, -1, "SRAI");

          inst_in <= assembler.RISCV32I(iADD,0,0,0,0);
          rs1_in <= sint2ulog32(2);
        when 16 =>
          test_against_sint(acc_out,2, "Add zero and positive");

          rs2_in <= sint2ulog32(-4);
        when 17 =>
          test_against_sint(acc_out, -2, "Add postive and negative");
          --this is a pass despite it saying fail maybe?
          inst_in <= assembler.RISCV32I(iSUB, 0, 0, 0, 0);
          
        when 18 =>
          test_against_sint(acc_out, 6, "Subtract negative from positive");
          
          rs2_in <= sint2ulog32(4);
        when 19 =>
          test_against_sint(acc_out, -2, "Subtract two positives");

          inst_in <= assembler.RISCV32I(iSLL, 0, 0, 0, 0);
          rs1_in <= sint2ulog32(1);
          rs2_in <= X"FFF00001";
        when 20 =>
          test_against_sint(acc_out, 2, "Ignore top bits in left shift");

          rs1_in <= X"00000100";
          rs2_in <= sint2ulog32(3);
        when 21 =>
          test_against_sint(acc_out, 2048, "sLL left shift 3");

          inst_in <= assembler.RISCV32I(iSLT, 0, 0, 0, 0);
          rs2_in <= sint2ulog32(0);
        when 22 =>
          test_1(acc_me, '0', "SLTI block select");
          
          inst_in <= assembler.RISCV32I(iSLT, 0, 0, 0, 0);
          rs1_in <= sint2ulog32(-4000);
          rs2_in <= sint2ulog32(-34);
        when 23 =>
          test_against_uint(acc_out, 1, "SLTI pass data");
          test_1(acc_me, '1', "SLTI pass select");

          inst_in <= assembler.RISCV32I(iSLTU, 0, 0, 0, 0);
          rs2_in <= sint2ulog32(34);
        when 24 =>
          test_1(acc_me, '1', "SLT block select");

          inst_in <= assembler.RISCV32I(iSLTU, 0, 0, 0, 0);

          rs1_in <= sint2ulog32(2); --largest unsigned
          rs2_in <= sint2ulog32(255);--random unsigned
        when 25 =>
          test_against_uint(acc_out, 1, "SLTU pass data");
          test_1(acc_me, '1', "SLTU pass select");

          inst_in <= assembler.RISCV32I(iXOR, 0, 0, 0, 0);
          rs1_in <= sint2ulog32(-1);
          rs2_in <= sint2ulog32(-1);
        when 26 =>
          test(acc_out, X"00000000", "iXOR 1");
          
          inst_in <= assembler.RISCV32I(iXOR, 0, 0, 0, 0);
          rs1_in <= sint2ulog32(20);
          rs2_in <= sint2ulog32(4);
        when 27 =>
          test_against_uint(acc_out, 16, "XOR 2");

          inst_in <= assembler.RISCV32I(iSLL,0,0,0,0);
          rs1_in <= sint2ulog32(2);
          rs2_in <= sint2ulog32(1);

        when 28 =>
          test_against_sint(acc_out, 4, "SLL");
          inst_in <= assembler.RISCV32I(iSRL, 0,0,0,0);
          
        when 29 =>
          test_against_sint(acc_out, 1, "SRL");
          inst_in <= assembler.RISCV32I(iSRA, 0,0,0,0);
          rs1_in <= sint2ulog32(-2);
          rs2_in <= sint2ulog32(1);

        when 30 =>
          test_against_sint(acc_out, -1, "SRA");

          inst_in <= assembler.RISCV32I(iORI,0,0,0,0);
          rs2_in <= sint2ulog32(0);
          rs1_in <= sint2ulog32(42534);
        when 31 =>
          test_against_sint(acc_out, 42534, "OR 1");
          
          inst_in <= assembler.RISCV32I(iOR,0,0,0,0); --should make
          rs2_in <= X"0000FFFF";
          rs1_in <= X"FFFF0000";
        when 32 =>
          test_against_sint(acc_out, -1 , "ORI 2"); -- should be all 1s
          
          inst_in <= assembler.RISCV32I(iAND,0,0,0,0);
          rs2_in <= sint2ulog32(0);
          rs1_in <= sint2ulog32(42534);
        when 33 =>
          test_against_sint(acc_out, 0, "AND 0");
          
          inst_in <= assembler.RISCV32I(iAND,0,0,0,0); --should make
                                                      --the imm all 1s
          rs2_in <= X"FFFFFFFF";
          rs1_in <= sint2ulog32(1500000);

        when 34 =>
          test_against_sint(acc_out, 1500000 , "AND 1");
          inst_in <= assembler.RISCV32I(iBEQ, 0,23,22,2000);

        when 35 =>
          test_1(acc_me, '0' , "test non-ALU instruction");
          
          
        when others => null;
      end case;
      

      wait for TbPeriod;

    end loop;
    -- Stop the clock and terminate the simulation
    TbSimEnded <= '1';
    wait;
  end process;

end tb;

sim/tb_integer_32_ALU.vcd
$date
  Tue Feb  2 13:54:37 2021
$end
$version
  GHDL v0
$end
$timescale
  1 fs
$end
$scope module standard $end
$upscope $end
$scope module std_logic_1164 $end
$upscope $end
$scope module numeric_std $end
$upscope $end
$scope module riscv_32i $end
$upscope $end
$scope module assembler $end
$upscope $end
$scope module helpers $end
$upscope $end
$scope module tb_helpers $end
$upscope $end
$scope module tb_integer_32_alu $end
$var reg 1 ! clk $end
$var reg 1 " rst $end
$var reg 32 # inst_in[31:0] $end
$var reg 32 $ rs1_in[31:0] $end
$var reg 32 % rs2_in[31:0] $end
$var reg 32 & acc_out[31:0] $end
$var reg 1 ' acc_me $end
$var reg 1 ( tbclock $end
$var reg 1 ) tbsimended $end
$scope module dut $end
$var reg 1 * clk $end
$var reg 1 + rst $end
$var reg 32 , inst_in[31:0] $end
$var reg 32 - rs1_in[31:0] $end
$var reg 32 . rs2_in[31:0] $end
$var reg 32 / acc_out[31:0] $end
$var reg 1 0 acc_me $end
$upscope $end
$upscope $end
$enddefinitions $end
#0
0!
0"
b00000000000000000000000000000000 #
b00000000000000000000000000000000 $
b00000000000000000000000000000000 %
b00000000000000000000000000000000 &
0'
0(
0)
0*
0+
b00000000000000000000000000000000 ,
b00000000000000000000000000000000 -
b00000000000000000000000000000000 .
b00000000000000000000000000000000 /
00
#100000000
1"
1+
#200000000
b00000110010000000000000000010011 #
b00000110010000000000000000010011 ,
#500000000
1!
b00000000000000000000000001100100 &
1'
1(
1*
b00000000000000000000000001100100 /
10
#1000000000
0!
0(
0*
#1200000000
b11101011101100000000000000010011 #
b00000000000000000000000000000001 $
b11101011101100000000000000010011 ,
b00000000000000000000000000000001 -
#1500000000
1!
b11111111111111111111111010111100 &
1(
1*
b11111111111111111111111010111100 /
#2000000000
0!
0(
0*
#2200000000
b00000000000100000010000000010011 #
b00000000000100000010000000010011 ,
#2500000000
1!
b00000000000000000000000000000001 &
0'
1(
1*
b00000000000000000000000000000001 /
00
#3000000000
0!
0(
0*
#3200000000
b11111101111000000010000000010011 #
b11111111111111111111000001100000 $
b11111101111000000010000000010011 ,
b11111111111111111111000001100000 -
#3500000000
1!
1'
1(
1*
10
#4000000000
0!
0(
0*
#4200000000
b00000010001000000011000000010011 #
b00000010001000000011000000010011 ,
#4500000000
1!
1(
1*
#5000000000
0!
0(
0*
#5200000000
b00001111111100000011000000010011 #
b00000000000000000000000000000010 $
b00001111111100000011000000010011 ,
b00000000000000000000000000000010 -
#5500000000
1!
1(
1*
#6000000000
0!
0(
0*
#6200000000
b11111111111100000100000000010011 #
b00000000000000000000000011001000 $
b11111111111100000100000000010011 ,
b00000000000000000000000011001000 -
#6500000000
1!
b11111111111111111111111100110111 &
1(
1*
b11111111111111111111111100110111 /
#7000000000
0!
0(
0*
#7200000000
b00000000000000000100000000010011 #
b00000000000000000000000000000000 $
b00000000000000000100000000010011 ,
b00000000000000000000000000000000 -
#7500000000
1!
b00000000000000000000000000000000 &
1(
1*
b00000000000000000000000000000000 /
#8000000000
0!
0(
0*
#8200000000
b00000000000000000110000000010011 #
b00000000000000001010011000100110 $
b00000000000000000110000000010011 ,
b00000000000000001010011000100110 -
#8500000000
1!
b00000000000000001010011000100110 &
1(
1*
b00000000000000001010011000100110 /
#9000000000
0!
0(
0*
#9200000000
b11111111111100000110000000010011 #
b11111111111111111111111111111111 $
b11111111111100000110000000010011 ,
b11111111111111111111111111111111 -
#9500000000
1!
b11111111111111111111111111111111 &
1(
1*
b11111111111111111111111111111111 /
#10000000000
0!
0(
0*
#10200000000
b00000000000000000111000000010011 #
b00000000000000001010011000100110 $
b00000000000000000111000000010011 ,
b00000000000000001010011000100110 -
#10500000000
1!
b00000000000000000000000000000000 &
1(
1*
b00000000000000000000000000000000 /
#11000000000
0!
0(
0*
#11200000000
b11111111111100000111000000010011 #
b00000000000000000011101010011000 $
b11111111111100000111000000010011 ,
b00000000000000000011101010011000 -
#11500000000
1!
b00000000000000000011101010011000 &
1(
1*
b00000000000000000011101010011000 /
#12000000000
0!
0(
0*
#12200000000
b00000000000100000001000000010011 #
b00000000000000000000000000000010 $
b00000000000100000001000000010011 ,
b00000000000000000000000000000010 -
#12500000000
1!
b00000000000000000000000000000100 &
1(
1*
b00000000000000000000000000000100 /
#13000000000
0!
0(
0*
#13200000000
b00000000000100000101000000010011 #
b00000000000100000101000000010011 ,
#13500000000
1!
b00000000000000000000000000000001 &
1(
1*
b00000000000000000000000000000001 /
#14000000000
0!
0(
0*
#14200000000
b01000000000100000101000000010011 #
b11111111111111111111111111111110 $
b01000000000100000101000000010011 ,
b11111111111111111111111111111110 -
#14500000000
1!
b11111111111111111111111111111111 &
1(
1*
b11111111111111111111111111111111 /
#15000000000
0!
0(
0*
#15200000000
b00000000000000000000000000110011 #
b00000000000000000000000000000010 $
b00000000000000000000000000110011 ,
b00000000000000000000000000000010 -
#15500000000
1!
b00000000000000000000000000000010 &
1(
1*
b00000000000000000000000000000010 /
#16000000000
0!
0(
0*
#16200000000
b11111111111111111111111111111100 %
b11111111111111111111111111111100 .
#16500000000
1!
b11111111111111111111111111111110 &
1(
1*
b11111111111111111111111111111110 /
#17000000000
0!
0(
0*
#17200000000
b01000000000000000000000000110011 #
b01000000000000000000000000110011 ,
#17500000000
1!
b00000000000000000000000000000110 &
1(
1*
b00000000000000000000000000000110 /
#18000000000
0!
0(
0*
#18200000000
b00000000000000000000000000000100 %
b00000000000000000000000000000100 .
#18500000000
1!
b11111111111111111111111111111110 &
1(
1*
b11111111111111111111111111111110 /
#19000000000
0!
0(
0*
#19200000000
b00000000000000000001000000110011 #
b00000000000000000000000000000001 $
b11111111111100000000000000000001 %
b00000000000000000001000000110011 ,
b00000000000000000000000000000001 -
b11111111111100000000000000000001 .
#19500000000
1!
b00000000000000000000000000000010 &
1(
1*
b00000000000000000000000000000010 /
#20000000000
0!
0(
0*
#20200000000
b00000000000000000000000100000000 $
b00000000000000000000000000000011 %
b00000000000000000000000100000000 -
b00000000000000000000000000000011 .
#20500000000
1!
b00000000000000000000100000000000 &
1(
1*
b00000000000000000000100000000000 /
#21000000000
0!
0(
0*
#21200000000
b00000000000000000010000000110011 #
b00000000000000000000000000000000 %
b00000000000000000010000000110011 ,
b00000000000000000000000000000000 .
#21500000000
1!
b00000000000000000000000000000001 &
0'
1(
1*
b00000000000000000000000000000001 /
00
#22000000000
0!
0(
0*
#22200000000
b11111111111111111111000001100000 $
b11111111111111111111111111011110 %
b11111111111111111111000001100000 -
b11111111111111111111111111011110 .
#22500000000
1!
1'
1(
1*
10
#23000000000
0!
0(
0*
#23200000000
b00000000000000000011000000110011 #
b00000000000000000000000000100010 %
b00000000000000000011000000110011 ,
b00000000000000000000000000100010 .
#23500000000
1!
1(
1*
#24000000000
0!
0(
0*
#24200000000
b00000000000000000000000000000010 $
b00000000000000000000000011111111 %
b00000000000000000000000000000010 -
b00000000000000000000000011111111 .
#24500000000
1!
1(
1*
#25000000000
0!
0(
0*
#25200000000
b00000000000000000100000000110011 #
b11111111111111111111111111111111 $
b11111111111111111111111111111111 %
b00000000000000000100000000110011 ,
b11111111111111111111111111111111 -
b11111111111111111111111111111111 .
#25500000000
1!
b00000000000000000000000000000000 &
1(
1*
b00000000000000000000000000000000 /
#26000000000
0!
0(
0*
#26200000000
b00000000000000000000000000010100 $
b00000000000000000000000000000100 %
b00000000000000000000000000010100 -
b00000000000000000000000000000100 .
#26500000000
1!
b00000000000000000000000000010000 &
1(
1*
b00000000000000000000000000010000 /
#27000000000
0!
0(
0*
#27200000000
b00000000000000000001000000110011 #
b00000000000000000000000000000010 $
b00000000000000000000000000000001 %
b00000000000000000001000000110011 ,
b00000000000000000000000000000010 -
b00000000000000000000000000000001 .
#27500000000
1!
b00000000000000000000000000000100 &
1(
1*
b00000000000000000000000000000100 /
#28000000000
0!
0(
0*
#28200000000
b00000000000000000101000000110011 #
b00000000000000000101000000110011 ,
#28500000000
1!
b00000000000000000000000000000001 &
1(
1*
b00000000000000000000000000000001 /
#29000000000
0!
0(
0*
#29200000000
b01000000000000000101000000110011 #
b11111111111111111111111111111110 $
b01000000000000000101000000110011 ,
b11111111111111111111111111111110 -
#29500000000
1!
b11111111111111111111111111111111 &
1(
1*
b11111111111111111111111111111111 /
#30000000000
0!
0(
0*
#30200000000
b00000000000000000110000000010011 #
b00000000000000001010011000100110 $
b00000000000000000000000000000000 %
b00000000000000000110000000010011 ,
b00000000000000001010011000100110 -
b00000000000000000000000000000000 .
#30500000000
1!
b00000000000000001010011000100110 &
1(
1*
b00000000000000001010011000100110 /
#31000000000
0!
0(
0*
#31200000000
b00000000000000000110000000110011 #
b11111111111111110000000000000000 $
b00000000000000001111111111111111 %
b00000000000000000110000000110011 ,
b11111111111111110000000000000000 -
b00000000000000001111111111111111 .
#31500000000
1!
b11111111111111111111111111111111 &
1(
1*
b11111111111111111111111111111111 /
#32000000000
0!
0(
0*
#32200000000
b00000000000000000111000000110011 #
b00000000000000001010011000100110 $
b00000000000000000000000000000000 %
b00000000000000000111000000110011 ,
b00000000000000001010011000100110 -
b00000000000000000000000000000000 .
#32500000000
1!
b00000000000000000000000000000000 &
1(
1*
b00000000000000000000000000000000 /
#33000000000
0!
0(
0*
#33200000000
b00000000000101101110001101100000 $
b11111111111111111111111111111111 %
b00000000000101101110001101100000 -
b11111111111111111111111111111111 .
#33500000000
1!
b00000000000101101110001101100000 &
1(
1*
b00000000000101101110001101100000 /
#34000000000
0!
0(
0*
#34200000000
b01111101011100000000100001100011 #
b01111101011100000000100001100011 ,
#34500000000
1!
0'
1(
1*
00
#35000000000
0!
0(
0*
#35200000000
#35500000000
1!
1(
1*
00
#36000000000
0!
0(
0*
#36200000000
1)
