hw/mem_access_tx.vhd
library IEEE;
use ieee.std_logic_1164.all;
use ieee.numeric_std.all;

library work;
use work.instructions.all;
use work.helpers.all;
--use work.tb_helpers.int2ulogic32;

entity mem_access_tx is
-- Sends load/store instructions and data to a memory cache
  generic(
    address_width : integer := 8; --size of each address in bits
    bit_width : integer := (32 - 1);
    bus_width: integer := 32 - 1
    );
  port(
    clk, rst : in std_ulogic;

    
    inst_enum_in  : in instruction_all;

    inst_in  : in instruction;
    inst_out : out instruction;
    
    rs1_in, rs2_in : in std_ulogic_vector(bit_width downto 0);

    rw : out std_ulogic; --Tell the cache if reading or writing, 0 for read 1
    --for write so on reset it will not 
    data_store  :out std_ulogic_vector(bus_width downto 0); --data to be stored
    address_out : out std_ulogic_vector(bit_width downto 0); --address to
                                                            --read/write to
    mem_len : out std_ulogic_vector(1 downto 0)
    );
end mem_access_tx;

architecture arch of mem_access_tx is
  alias op_code :std_ulogic_vector(6 downto 0) is inst_in(6 downto 0);
  --immediate for load instructions (I type)
  alias I_imm   :std_ulogic_vector(11 downto 0) is inst_in(31 downto 20);
  
    
begin
  process(clk)
    variable not_select : std_logic; -- used as a bool 
    variable imm : std_ulogic_vector(bit_width downto 0);
    variable overflow : signed(bit_width + 1 downto 0); -- deal with overflow
  begin
    
    if rst = '0' then
      inst_out <= (others => '0');
      data_store <= (others => '0');
      rw <= '0';
      mem_len <= (others => '0');
      address_out <= (others => '0');
      
    elsif rising_edge(clk) then
      inst_out <= inst_in; -- feed inst through in line with clock cycle to rx
      
      not_select := '0';

      case inst_enum_in is
        when iLW | iSW =>
          mem_len <= "11";
        when iLB | iLBU | iSB=>
          mem_len <= "00";
        when iLH| iLHU | iSH =>
          mem_len <= "01";			
        when others =>
          -- output nothing
          not_select := '1';
      end case;	

      if not_select = '1' then
        rw <= '0'; --set read so no wrong data is accidently saved
        --rest of data doesn't matter so will be ignored.
        address_out <= (others => '0'); -- set address to 0 when nothing happening
      else
        --find imm
          if op_code = "0000011" then --load opcode
            rw <= '0';
            imm(31 downto 12) := (others => i_imm(11)); 
            imm(11 downto 0)  := i_imm; --simple sign extend
                                                             --using numeric_std
          else -- if neither of the first two, result will be a store
            imm(11 downto 5) := inst_in(31 downto 25);
            imm(4 downto 0) := inst_in(11 downto 7);
            imm(bit_width downto 12) := (others => imm(11)); --sign extend
            data_store <= rs2_in; --set data to be saved
            rw <= '1';
          end if;
          --set address of read or write
          overflow := signed(imm) + signed('0' & rs1_in);
          address_out <= std_ulogic_vector(overflow(bit_width downto 0));
      end if;
    end if;
  end process;
end arch;

tb/mem_access_tx_tb.vhd
library ieee;
use ieee.std_logic_1164.all;
use work.instructions.all;
use work.helpers.all;
use work.tb_helpers.all;
use work.assembler.all;


entity tb_mem_access_tx is
    generic(
    address_width : integer := 8; --size of each address in bits
    bit_width : integer := (32 - 1);
    bus_width: integer := 32 - 1
    );
end tb_mem_access_tx;


architecture tb of tb_mem_access_tx is

    component mem_access_tx
        port (clk         : in std_ulogic;
              rst         : in std_ulogic;
              inst_in     : in instruction;
              inst_out    : out instruction;
              rs1_in      : in std_ulogic_vector (bit_width downto 0);
              rs2_in      : in std_ulogic_vector (bit_width downto 0);
              rw          : out std_ulogic;
              data_store  : out std_ulogic_vector (bus_width downto 0);
              address_out : out std_ulogic_vector (bit_width downto 0);
              mem_len     : out std_ulogic_vector (1  downto 0));
    end component;

    signal clk         : std_ulogic;
    signal rst         : std_ulogic;
    signal inst_in     : instruction;
    signal inst_out    : instruction;
    signal rs1_in      : std_ulogic_vector (bit_width downto 0);
    signal rs2_in      : std_ulogic_vector (bit_width downto 0);
    signal rw          : std_ulogic;
    signal data_store  : std_ulogic_vector (bus_width downto 0);
    signal address_out : std_ulogic_vector (bit_width downto 0);
    signal mem_len     : std_ulogic_vector (1 downto 0);

    constant TbPeriod : time := 1000 ns; -- EDIT Put right period here
    signal TbClock : std_logic := '0';
    signal TbSimEnded : std_logic := '0';

begin

    dut : mem_access_tx
    port map (clk         => clk,
              rst         => rst,
              inst_in     => inst_in,
              inst_out    => inst_out,
              rs1_in      => rs1_in,
              rs2_in      => rs2_in,
              rw          => rw,
              data_store  => data_store,
              address_out => address_out,
              mem_len     => mem_len);

    -- Clock generation
    TbClock <= not TbClock after TbPeriod/2 when TbSimEnded /= '1' else '0';
    clk <= TbClock;

    stimuli : process
    begin
        --initialization 
        inst_in <= (others => '0');
        rs1_in <= (others => '0');
        rs2_in <= (others => '0');

        -- Reset generation
        rst <= '0';
        wait for 100 ns;
        rst <= '1';
        wait for 100 ns;

        for i in 0 to 8 loop
          case i is
            when 0 =>
              inst_in <= RISCV32I(iLB,0,0,0,43);
              
            when 1 =>
              test(inst_out, RISCV32I(iLB,0,0,0,43), "inst passthrough");
              test_against_uint(address_out, 43, "Address add naturals, load");
              test_against_uint(mem_len, 0, "LB memory length test");
              test_1(rw, '0', "set read");
              
              inst_in <= RISCV32I(iLH, 0 ,0, 0, 1); 
              rs1_in <= X"80000000";
            when 2 =>
              test(address_out, X"80000001" , "Add two positives, load");
              test_against_uint(mem_len, 1, "LH memory length test");

              inst_in <= RISCV32I(iLW, 0 ,0, 0, -2);
              rs1_in <= sint2ulog32(100);
            when 3 =>
              test_against_uint(address_out, 98, "Positive and negative, load");
              test_against_uint(mem_len, 3, "LW memory length test");

              inst_in <= RISCV32I(iSB,0 ,0, 0,4);
              rs2_in <= sint2ulog32(78693); -- random number
            when 4 =>
              test_against_uint(address_out, 104 , "Add two positives, store");
              test_against_uint(data_store, 78693 , "store data");
              test_against_uint(mem_len, 0, "SB memory length test");
              test_1(rw, '1', "set write");
              
              inst_in <= RISCV32I(iSH, 0 ,0, 0, -2);
            when 5 =>
              test_against_uint(address_out, 98, "Positive and negative, store");
              test_against_uint(mem_len, 1, "SH memory length test");

              inst_in <= RISCV32I(iSW, 0,0,0,0);
            when 6 =>
              test_against_uint(address_out, 100, "add two naturals, store");
              test_against_uint(mem_len, 3, "SW memory length test");

              inst_in <= RISCV32I(iJAL, 5,5 ,5 ,5);
            when 7 =>
              test(inst_out, RISCV32I(iJAL, 5,5 ,5 ,5), "pass unused instruction");
              test_1(rw, '0', "set read for unrelated op");
            when others =>
              null;
          end case;
          wait for TbPeriod;
        end loop;
        
        -- Stop the clock and hence terminate the simulation
        TbSimEnded <= '1';
        wait;
    end process;

end tb;

sim/tb_mem_access_tx.vcd
$date
  Mon Feb  8 15:53:17 2021
$end
$version
  GHDL v0
$end
$timescale
  1 fs
$end
$scope module standard $end
$upscope $end
$scope module std_logic_1164 $end
$upscope $end
$scope module numeric_std $end
$upscope $end
$scope module riscv_32i $end
$upscope $end
$scope module helpers $end
$upscope $end
$scope module tb_helpers $end
$upscope $end
$scope module assembler $end
$upscope $end
$scope module tb_mem_access_tx $end
$var reg 1 ! clk $end
$var reg 1 " rst $end
$var reg 32 # inst_in[31:0] $end
$var reg 32 $ inst_out[31:0] $end
$var reg 32 % rs1_in[31:0] $end
$var reg 32 & rs2_in[31:0] $end
$var reg 1 ' rw $end
$var reg 32 ( data_store[31:0] $end
$var reg 32 ) address_out[31:0] $end
$var reg 2 * mem_len[1:0] $end
$var reg 1 + tbclock $end
$var reg 1 , tbsimended $end
$scope module dut $end
$var reg 1 - clk $end
$var reg 1 . rst $end
$var reg 32 / inst_in[31:0] $end
$var reg 32 0 inst_out[31:0] $end
$var reg 32 1 rs1_in[31:0] $end
$var reg 32 2 rs2_in[31:0] $end
$var reg 1 3 rw $end
$var reg 32 4 data_store[31:0] $end
$var reg 32 5 address_out[31:0] $end
$var reg 2 6 mem_len[1:0] $end
$upscope $end
$upscope $end
$enddefinitions $end
#0
0!
0"
b00000000000000000000000000000000 #
b00000000000000000000000000000000 $
b00000000000000000000000000000000 %
b00000000000000000000000000000000 &
0'
b00000000000000000000000000000000 (
b00000000000000000000000000000000 )
b00 *
0+
0,
0-
0.
b00000000000000000000000000000000 /
b00000000000000000000000000000000 0
b00000000000000000000000000000000 1
b00000000000000000000000000000000 2
03
b00000000000000000000000000000000 4
b00000000000000000000000000000000 5
b00 6
#100000000
1"
1.
#200000000
b00000010101100000000000000000011 #
b00000010101100000000000000000011 /
#500000000
1!
b00000010101100000000000000000011 $
b00000000000000000000000000101011 )
1+
1-
b00000010101100000000000000000011 0
b00000000000000000000000000101011 5
#1000000000
0!
0+
0-
#1200000000
b00000000000100000001000000000011 #
b10000000000000000000000000000000 %
b00000000000100000001000000000011 /
b10000000000000000000000000000000 1
#1500000000
1!
b00000000000100000001000000000011 $
b10000000000000000000000000000001 )
b01 *
1+
1-
b00000000000100000001000000000011 0
b10000000000000000000000000000001 5
b01 6
#2000000000
0!
0+
0-
#2200000000
b11111111111000000010000000000011 #
b00000000000000000000000001100100 %
b11111111111000000010000000000011 /
b00000000000000000000000001100100 1
#2500000000
1!
b11111111111000000010000000000011 $
b00000000000000000000000001100010 )
b11 *
1+
1-
b11111111111000000010000000000011 0
b00000000000000000000000001100010 5
b11 6
#3000000000
0!
0+
0-
#3200000000
b00000000000000000000001000100011 #
b00000000000000010011001101100101 &
b00000000000000000000001000100011 /
b00000000000000010011001101100101 2
#3500000000
1!
b00000000000000000000001000100011 $
1'
b00000000000000010011001101100101 (
b00000000000000000000000001101000 )
b00 *
1+
1-
b00000000000000000000001000100011 0
13
b00000000000000010011001101100101 4
b00000000000000000000000001101000 5
b00 6
#4000000000
0!
0+
0-
#4200000000
b11111110000000000001111100100011 #
b11111110000000000001111100100011 /
#4500000000
1!
b11111110000000000001111100100011 $
b00000000000000000000000001100010 )
b01 *
1+
1-
b11111110000000000001111100100011 0
b00000000000000000000000001100010 5
b01 6
#5000000000
0!
0+
0-
#5200000000
b00000000000000000010000000100011 #
b00000000000000000010000000100011 /
#5500000000
1!
b00000000000000000010000000100011 $
b00000000000000000000000001100100 )
b11 *
1+
1-
b00000000000000000010000000100011 0
b00000000000000000000000001100100 5
b11 6
#6000000000
0!
0+
0-
#6200000000
b00000000000000000000001011101111 #
b00000000000000000000001011101111 /
#6500000000
1!
b00000000000000000000001011101111 $
0'
1+
1-
b00000000000000000000001011101111 0
03
#7000000000
0!
0+
0-
#7200000000
#7500000000
1!
1+
1-
#8000000000
0!
0+
0-
#8200000000
#8500000000
1!
1+
1-
#9000000000
0!
0+
0-
#9200000000
1,
